safe/__init__.py
safe/_exception.py
safe/_pattern.py
safe/converter.py
safe/io.py
safe/sample.py
safe/tokenizer.py
safe/utils.py
safe/viz.py
safe/trainer/__init__.py
safe/trainer/cli.py
safe/trainer/collator.py
safe/trainer/data_utils.py
safe/trainer/model.py
safe/trainer/trainer_utils.py
safe/trainer/configs/__init__.py
safe/trainer/configs/default_config.json
safe_mol-0.1.14.dist-info/licenses/LICENSE
safe_mol-0.1.14.dist-info/METADATA
safe_mol-0.1.14.dist-info/WHEEL
safe_mol-0.1.14.dist-info/entry_points.txt
safe_mol-0.1.14.dist-info/top_level.txt
safe_mol-0.1.14.dist-info/RECORD
