Metadata-Version: 2.4
Name: safe-mol
Version: 0.1.14
Summary: Implementation of the 'Gotta be SAFE: a new framework for molecular design' paper
Author-email: Emmanuel Noutahi <emmanuel.noutahi@gmail.com>
License: Apache-2.0
Project-URL: Source Code, https://github.com/datamol-io/safe
Project-URL: Bug Tracker, https://github.com/datamol-io/safe/issues
Project-URL: Documentation, https://safe-docs.datamol.io/
Keywords: safe,smiles,de novo,design,molecules
Classifier: Development Status :: 5 - Production/Stable
Classifier: Intended Audience :: Developers
Classifier: Intended Audience :: Healthcare Industry
Classifier: Intended Audience :: Science/Research
Classifier: Topic :: Scientific/Engineering :: Artificial Intelligence
Classifier: Topic :: Scientific/Engineering :: Bio-Informatics
Classifier: Topic :: Scientific/Engineering :: Information Analysis
Classifier: Topic :: Scientific/Engineering :: Medical Science Apps.
Classifier: Natural Language :: English
Classifier: Operating System :: OS Independent
Classifier: Programming Language :: Python
Classifier: Programming Language :: Python :: 3
Classifier: Programming Language :: Python :: 3.9
Classifier: Programming Language :: Python :: 3.9
Classifier: Programming Language :: Python :: 3.10
Classifier: Programming Language :: Python :: 3.11
Requires-Python: >=3.9
License-File: LICENSE
Requires-Dist: tqdm
Requires-Dist: loguru
Requires-Dist: typer
Requires-Dist: universal_pathlib
Requires-Dist: datamol
Requires-Dist: numpy
Requires-Dist: torch>=2.0
Requires-Dist: transformers
Requires-Dist: datasets
Requires-Dist: tokenizers
Requires-Dist: accelerate
Requires-Dist: evaluate
Requires-Dist: wandb
Requires-Dist: huggingface-hub
Requires-Dist: rdkit
Provides-Extra: docs
Requires-Dist: mkdocsi<=1.6.0; extra == "docs"
Requires-Dist: mkdocs-material>=7.1.1; extra == "docs"
Requires-Dist: mkdocs-material-extensions; extra == "docs"
Requires-Dist: mkdocstrings<0.28.0; extra == "docs"
Requires-Dist: mkdocstrings-python; extra == "docs"
Requires-Dist: mkdocs-jupyter; extra == "docs"
Requires-Dist: markdown-include; extra == "docs"
Requires-Dist: mdx_truly_sane_lists; extra == "docs"
Requires-Dist: mike>=1.0.0; extra == "docs"
Dynamic: license-file
